kiraak/__init__.py
kiraak/__main__.py
kiraak/add_orders.py
kiraak/api.py
kiraak/catalog.py
kiraak/cli.py
kiraak/compare.py
kiraak/config.py
kiraak/difflib.py
kiraak/get_catalog.py
kiraak/main.py
kiraak/mapping.py
kiraak/order.py
kiraak/sync.py
kiraak/__pycache__/__init__.cpython-310.pyc
kiraak/__pycache__/api.cpython-310.pyc
kiraakcli-3.0.0.dist-info/METADATA
kiraakcli-3.0.0.dist-info/WHEEL
kiraakcli-3.0.0.dist-info/entry_points.txt
kiraakcli-3.0.0.dist-info/top_level.txt
kiraakcli-3.0.0.dist-info/RECORD
