Metadata-Version: 2.1
Name: kiraakcli
Version: 3.0.0
Summary: Add orders to the Kiraak API
Home-page: https://github.com/Vthechamp22
Author: Vthechamp
Author-email: parashar.xtra@gmail.com
License: MIT
Platform: UNKNOWN
Classifier: License :: OSI Approved :: MIT License
Classifier: Programming Language :: Python :: 3
Classifier: Programming Language :: Python :: 3.7
Requires-Dist: requests
Requires-Dist: click
Requires-Dist: openpyxl
Requires-Dist: colorama
Requires-Dist: rich
Requires-Dist: woocommerce
